flask_qiniustoraging.py
Flask_QiniuStoraging-0.1.1.dist-info/LICENSE
Flask_QiniuStoraging-0.1.1.dist-info/METADATA
Flask_QiniuStoraging-0.1.1.dist-info/WHEEL
Flask_QiniuStoraging-0.1.1.dist-info/top_level.txt
Flask_QiniuStoraging-0.1.1.dist-info/RECORD
