Metadata-Version: 2.1
Name: Flask-QiniuStoraging
Version: 0.1.1
Summary: Qiniu object storage for flask
Home-page: https://github.com/stravel611/flask_qiniustoraging
Author: Yilin Liu
Author-email: liuyilin611@qq.com
License: MIT
Keywords: flask extension qiniu
Platform: any
Classifier: Development Status :: 3 - Alpha
Classifier: Environment :: Web Environment
Classifier: Intended Audience :: Developers
Classifier: License :: OSI Approved :: MIT License
Classifier: Programming Language :: Python
Classifier: Topic :: Internet :: WWW/HTTP :: Dynamic Content
Classifier: Topic :: Software Development :: Libraries :: Python Modules
Requires-Dist: Flask
Requires-Dist: qiniu
